README.txt
setup.py
changes/changes.txt
changes/history.txt
svndjango/__init__.py
svndjango/models.py
svndjango/sven.py
svndjango.egg-info/PKG-INFO
svndjango.egg-info/SOURCES.txt
svndjango.egg-info/dependency_links.txt
svndjango.egg-info/entry_points.txt
svndjango.egg-info/not-zip-safe
svndjango.egg-info/requires.txt
svndjango.egg-info/top_level.txt