Metadata-Version: 1.0
Name: svndjango
Version: 0.3
Summary: automatic backup of django model instances to a subversion repository
Home-page: UNKNOWN
Author: Ethan Jucovy
Author-email: ejucovy@gmail.com
License: GPL
Platform: UNKNOWN
Classifier: Development Status :: 3 - Alpha
Classifier: Environment :: Web Environment
Classifier: Intended Audience :: Developers
Classifier: Programming Language :: Python
Classifier: Framework :: Django
